README.md
setup.cfg
setup.py
sensorialytics/__init__.py
sensorialytics.egg-info/PKG-INFO
sensorialytics.egg-info/SOURCES.txt
sensorialytics.egg-info/dependency_links.txt
sensorialytics.egg-info/requires.txt
sensorialytics.egg-info/top_level.txt
sensorialytics/decorators/__init__.py
sensorialytics/helpers/__init__.py
sensorialytics/helpers/dates.py
sensorialytics/helpers/exceptions.py
sensorialytics/helpers/sensoria_io_client.py
sensorialytics/helpers/timer.py
sensorialytics/helpers/tools.py
sensorialytics/mathematics/__init__.py
sensorialytics/mathematics/constants.py
sensorialytics/mathematics/functions.py
sensorialytics/mathematics/point.py
sensorialytics/mathematics/polynomial.py
sensorialytics/mathematics/tools.py
sensorialytics/plots/__init__.py
sensorialytics/plots/plots.py
sensorialytics/preprocessing/__init__.py
sensorialytics/preprocessing/clustering.py
sensorialytics/preprocessing/encoders.py
sensorialytics/preprocessing/manipulations.py
sensorialytics/preprocessing/scalers.py
sensorialytics/preprocessing/tools.py
sensorialytics/readers/__init__.py
sensorialytics/readers/core_data.py
sensorialytics/readers/events.py
sensorialytics/readers/fitfile.py
sensorialytics/readers/helper.py
sensorialytics/readers/session.py
sensorialytics/readers/sessions.py
sensorialytics/sensors/__init__.py
sensorialytics/sensors/pressure.py
sensorialytics/sensors/sensor.py
sensorialytics/signals/__init__.py
sensorialytics/signals/detectors.py
sensorialytics/signals/filters.py
sensorialytics/signals/image.py