Metadata-Version: 1.1
Name: sensorialytics
Version: 1.0.24
Summary: Sensoria python library
Home-page: UNKNOWN
Author: Stefano Rossotti
Author-email: stefano@sensoriainc.com
License: MIT
Keywords: sensoria,analytics
Platform: UNKNOWN
Classifier: Development Status :: 5 - Production/Stable
Classifier: Intended Audience :: Developers
Classifier: Topic :: Software Development :: Build Tools
Classifier: License :: OSI Approved :: MIT License
Classifier: Programming Language :: Python :: 3
Classifier: Programming Language :: Python :: 3.4
Classifier: Programming Language :: Python :: 3.5
Classifier: Programming Language :: Python :: 3.6
Classifier: Programming Language :: Python :: 3.7
